htyy/D3Dcompiler_47.dll
htyy/Microphone.py
htyy/ModifyProcessCommandLine.pyd
htyy/Qt6Core.dll
htyy/Qt6Gui.dll
htyy/Qt6Network.dll
htyy/Qt6Pdf.dll
htyy/Qt6Svg.dll
htyy/Qt6Widgets.dll
htyy/QtWebEngineProcess.exe
htyy/__init__.py
htyy/__test__.py
htyy/_a.py
htyy/_b.py
htyy/_h7z.py
htyy/_hyy.py
htyy/_path.py
htyy/_system.py
htyy/_test.py
htyy/_test_translation.py
htyy/_wallpaper.py
htyy/client.py
htyy/extensions.py
htyy/gui.pyd
htyy/gui.pyi
htyy/message.py
htyy/modules.py
htyy/opengl32sw.dll
htyy/pyos.pyd
htyy/pyos.pyi
htyy/qt.conf
htyy/qwindows.dll
htyy/reponse.py
htyy/request.py
htyy/test.mp3
htyy/version.py
htyy/websys.py
htyy/windll.py
htyy/winp.py
htyy/__pycache__/Hoth.cpython-311.pyc
htyy/__pycache__/__init__.cpython-311.pyc
htyy/__pycache__/_path.cpython-311.pyc
htyy/__pycache__/client.cpython-311.pyc
htyy/__pycache__/extensions.cpython-311.pyc
htyy/__pycache__/message.cpython-311.pyc
htyy/__pycache__/reponse.cpython-311.pyc
htyy/__pycache__/request.cpython-311.pyc
htyy/__pycache__/version.cpython-311.pyc
htyy/__pycache__/windll.cpython-311.pyc
htyy/_infront/_Hoth_d.py
htyy/_infront/__init__.py
htyy/_infront/__pycache__/_Hoth_d.cpython-311.pyc
htyy/_infront/__pycache__/__init__.cpython-311.pyc
htyy/_infront/_htyy_d/__init__.py
htyy/_infront/_htyy_d/_message_d.py
htyy/_infront/_htyy_d/htyy.py
htyy/_infront/_htyy_d/windll.py
htyy/_infront/_htyy_d/windll.pyi
htyy/_infront/_htyy_d/__pycache__/__init__.cpython-311.pyc
htyy/_infront/_htyy_d/__pycache__/_message_d.cpython-311.pyc
htyy/_infront/_htyy_d/__pycache__/windll.cpython-311.pyc
htyy/auto/Process.py
htyy/auto/_wx.py
htyy/auto/htyywinauto.py
htyy/auto/wx.pyi
htyy/generic/qtuiotouchplugin.dll
htyy/hpyy/__init__.py
htyy/hpyy/__pycache__/__init__.cpython-311.pyc
htyy/hpyy/hlob/__init__.py
htyy/hpyy/hlob/utils.py
htyy/hpyy/hlob/__pycache__/__init__.cpython-311.pyc
htyy/hpyy/hlob/__pycache__/utils.cpython-311.pyc
htyy/hpyy/hlob/core/__init__.py
htyy/hpyy/hlob/core/matcher.py
htyy/hpyy/hlob/core/scanner.py
htyy-0.1.6.dist-info/LICENSE.txt
htyy-0.1.6.dist-info/METADATA
htyy-0.1.6.dist-info/WHEEL
htyy-0.1.6.dist-info/entry_points.txt
htyy-0.1.6.dist-info/top_level.txt
htyy-0.1.6.dist-info/RECORD
