Metadata-Version: 2.1
Name: htyy
Version: 0.1.6
Summary: htyy - All-in-one productivity tools
Author: huang yi yi
Author-email: 363766687@qq.com
Project-URL: Source, https://github.com/hyy-PROG/htyy
Classifier: Development Status :: 4 - Beta
Classifier: Environment :: Console
Classifier: Intended Audience :: End Users/Desktop
Classifier: Intended Audience :: System Administrators
Classifier: License :: OSI Approved :: MIT License
Classifier: Operating System :: Microsoft :: Windows
Classifier: Operating System :: POSIX :: Linux
Classifier: Operating System :: MacOS
Classifier: Programming Language :: Python :: 3
Classifier: Programming Language :: Python :: 3.7
Classifier: Programming Language :: Python :: 3.8
Classifier: Programming Language :: Python :: 3.9
Classifier: Programming Language :: Python :: 3.10
Classifier: Topic :: Utilities
Requires-Python: >=3.6
License-File: LICENSE.txt
Requires-Dist: watchdog
Requires-Dist: paramiko
Requires-Dist: pycryptodome
Requires-Dist: uiautomation
Requires-Dist: pywin32
Requires-Dist: psutil
Requires-Dist: rich
Requires-Dist: plyer
Requires-Dist: mpmath
Requires-Dist: miniaudio
Requires-Dist: argostranslate
Requires-Dist: googletrans
Requires-Dist: pyautogui
Requires-Dist: py7zr
Requires-Dist: cryptography
Requires-Dist: requests>=2.25.1
Requires-Dist: tqdm>=4.60.0
Requires-Dist: colorama>=0.4.4
